chem_classification/__init__.py
chem_classification/importSmiles.py
chem_classification/similarity_classification.py
chem_classification-0.0.3.dist-info/LICENSE
chem_classification-0.0.3.dist-info/METADATA
chem_classification-0.0.3.dist-info/WHEEL
chem_classification-0.0.3.dist-info/entry_points.txt
chem_classification-0.0.3.dist-info/top_level.txt
chem_classification-0.0.3.dist-info/RECORD
